certbot_onion-0.4.0.dist-info/METADATA
certbot_onion-0.4.0.dist-info/WHEEL
certbot_onion-0.4.0.dist-info/entry_points.txt
certbot_onion-0.4.0.dist-info/licenses/LICENSE.md
certbot_onion_rust/__init__.py
certbot_onion_rust/certbot_onion_rust.cpython-38-i386-linux-gnu.so
certbot_onion-0.4.0.dist-info/RECORD
