Metadata-Version: 2.4
Name: certbot-onion
Version: 0.4.0
Summary: Certbot authenticator plugin for the onion-csr-01 challenge
Author-email: Q Misell <q@as207960.net>
License: MIT
Project-URL: Homepage, https://acmeforonions.org
Project-URL: Repository, https://github.com/AS207960/certbot-onion
License-File: LICENSE.md
Requires-Dist: certbot>=4.0.0
Dynamic: license-file
